CONTRIBUTING.md
DEVELOPMENT.md
LICENSE
MANIFEST.in
NOTICES
README.md
requirements.txt
setup.cfg
setup.py
versioneer.py
moldesign/.dockerignore
moldesign/HISTORY.rst
moldesign/README.md
moldesign/__init__.py
moldesign/__main__.py
moldesign/_version.py
moldesign/chemjson.py
moldesign/data.py
moldesign/exceptions.py
moldesign/fileio.py
moldesign/mathutils.py
moldesign/method.py
moldesign/parameters.py
moldesign.egg-info/PKG-INFO
moldesign.egg-info/SOURCES.txt
moldesign.egg-info/dependency_links.txt
moldesign.egg-info/requires.txt
moldesign.egg-info/top_level.txt
moldesign/_notebooks/.gitattributes
moldesign/_notebooks/.gitignore
moldesign/_notebooks/Example 1. Build and simulate DNA.ipynb
moldesign/_notebooks/Example 2. UV-vis absorption spectra.ipynb
moldesign/_notebooks/Example 3. Simulating a crystal structure.ipynb
moldesign/_notebooks/Example 4. HIV Protease bound to an inhibitor.ipynb
moldesign/_notebooks/Example 5. Enthalpic barriers.ipynb
moldesign/_notebooks/Getting Started.ipynb
moldesign/_notebooks/Tutorial 1. Making a molecule.ipynb
moldesign/_notebooks/Tutorial 2. Biochemical basics.ipynb
moldesign/_notebooks/Tutorial 3. Quantum Chemistry.ipynb
moldesign/_notebooks/.building/Dexter_alkane.ipynb
moldesign/_notebooks/.building/Guided tour.ipynb
moldesign/_notebooks/.building/Header.ipynb
moldesign/_notebooks/.building/Parallel.ipynb
moldesign/_notebooks/.building/The harmonic oscillator.ipynb
moldesign/_notebooks/.building/Units and gravity.ipynb
moldesign/_notebooks/.building/buckyball.ipynb
moldesign/_notebooks/data/1bna.pdb
moldesign/_notebooks/data/3AID.pdb
moldesign/_notebooks/data/bipyridine.sdf
moldesign/_notebooks/data/buckyball.pdb
moldesign/_notebooks/data/butane.xyz
moldesign/_notebooks/data/nuc.inpcrd
moldesign/_notebooks/data/nuc.pdb
moldesign/_notebooks/data/nuc.prmtop
moldesign/_notebooks/data/octane.xyz
moldesign/_notebooks/data/solar.csv
moldesign/_notebooks/img/Header.png
moldesign/_notebooks/img/Molecules.png
moldesign/_notebooks/img/Top.png
moldesign/_notebooks/img/butadiene_orbs.png
moldesign/_notebooks/img/dna.png
moldesign/_notebooks/img/holliday.png
moldesign/_notebooks/img/protease.png
